Internet_search.py
mseep_internetsearch_mcp_server-0.1.3.dist-info/licenses/LICENSE
mseep_internetsearch_mcp_server-0.1.3.dist-info/METADATA
mseep_internetsearch_mcp_server-0.1.3.dist-info/WHEEL
mseep_internetsearch_mcp_server-0.1.3.dist-info/top_level.txt
mseep_internetsearch_mcp_server-0.1.3.dist-info/RECORD
