Metadata-Version: 2.4
Name: mseep-internetsearch-mcp-server
Version: 0.1.3
Summary: Add your description here
Author-email: mseep <support@skydeck.ai>
Requires-Python: >=3.13
License-File: LICENSE
Requires-Dist: httpx>=0.28.1
Requires-Dist: mcp[cli]>=1.5.0
Requires-Dist: requests>=2.32.3
Dynamic: license-file
